{"authors":["Linette Lopez","Prashanth Perumal"],"date_download":"2018-10-30 23:04:11","date_modify":"2018-10-30 23:04:11","date_publish":"2016-12-08 00:00:00","description":"It's called 'Have Your Cake and Eat it Too.'","filename":"data/vaneerConsumption/DavidEinhornRobinHoodBayerandMonsantoPresentations.json","image_url":"https://amp.businessinsider.com/images/5849a244ba6eb671018b831a-640-320.png","language":null,"localpath":"/home/avsp_here/news-please-repo//data/2018/10/30/businessinsider.com/_david-einhorn-robin-hood-bayer-and-monsanto-presentations-2016-12_1540940651.html","title":"David Einhorn Robin Hood Bayer and Monsanto Presentations","title_page":"    David Einhorn Robin Hood Bayer and Monsanto Presentations - Business Insider\n","title_rss":"NULL","source_domain":"businessinsider.com","text":"David Einhorn, president of Greenlight Capital speaks at the Sohn Investment Conference in New York Thomson Reuters Last week, famed investor David Einhorn of hedge fund Greenlight Capital gave a presentation at the exclusive Robin Hood Investors Conference (it supports the charitable foundation of the same name, check that out here).\nIn it, he explained his long thesis for pharmaceutical giant, Bayer.\nLast year Bayer spun off its chemicals company, Covestro, and then in September announced a deal to take over seed-maker Monsanto.\nThat deal is pending approval from a dizzying number of regulators around the world.\nNow, here's the crux of why Einhorn likes Bayer in all of this:\n\"Whether they make it to the altar, or get thwarted along the way, there's going to be a celebration for Bayer shareholders either way. With cake. And we like cake,\" he said.\nScroll down to get his full take on why.","url":"https://www.businessinsider.com/david-einhorn-robin-hood-bayer-and-monsanto-presentations-2016-12"}
