{"authors":[],"date_download":"2018-10-22 20:52:23","date_modify":"2018-10-22 20:52:23","date_publish":"2014-06-03 13:46:14","description":"DVF is helping Google Glass move into the world of high fashion.","filename":"data/vaneerConsumption/GoogleGlassandDianevonFurstenbergUnveilHauteSpecs.json","image_url":"https://media1.s-nbcnews.com/j/newscms/2014_23/483841/dvf1_8eb0dc698d11c6b76e99b92c5de65073.1200;630;7;70;5.jpg","language":"en","localpath":"/home/avsp_here/news-please-repo//data/2018/10/22/nbcnews.com/tech_gadgets_google-glass-diane-von-furstenberg-unveil-haute-specs-n121196_1540241543.html","title":"Google Glass and Diane von Furstenberg Unveil Haute Specs","title_page":"Google Glass and Diane von Furstenberg Unveil Haute Specs","title_rss":"NULL","source_domain":"nbcnews.com","text":"Breaking News Emails Get breaking news alerts and special reports. The news and stories that matter, delivered weekday mornings.\nGoogle Glass has officially entered the world of high fashion thanks to a collaboration with designer Diane von Furstenberg.\nWhen first released in 2013, Google Glass was not exactly known for being a stylish accessory. It was the kind of thing a middle-aged Silicon Valley millionaire might wear while riding a Segway.\nThen came the the Titanium Collection, a line of hipster-friendly specs that cost an extra $225. After that, Google partnered with Ray-Ban and Oakley to create wearable computers even a jock could love. Now fashionistas finally have their own Google Glass.","url":"https://www.nbcnews.com/tech/gadgets/google-glass-diane-von-furstenberg-unveil-haute-specs-n121196"}
