{"authors":["Lianna Brinded"],"date_download":"2018-10-31 00:08:43","date_modify":"2018-10-31 00:08:43","date_publish":"2016-12-03 00:00:00","description":"Crispin Odey saw his fortune fall massively in 2016.","filename":"data/vaneerConsumption/The13richesthedgefundmanagersinBritain.json","image_url":"https://amp.businessinsider.com/images/58427b84dd089530448b48fe-960-480.jpg","language":null,"localpath":"/home/avsp_here/news-please-repo//data/2018/10/30/businessinsider.com/_sunday-times-rich-list-2016-hedge-fund-managers-uk-britain-2016-12_1540944523.html","title":"The 13 richest hedge fund managers in Britain","title_page":"    Sunday Times Rich List 2016: Hedge fund managers - Business Insider\n","title_rss":"NULL","source_domain":"businessinsider.com","text":"Michael Hintze, CEO of CQS hedge fund. Reuters The last couple of years have been rocky for hedge fund managers following a rollercoaster ride in the commodities markets.\nHedge fund manager Crispin Odey saw his wealth melt by £200 million ($287 million) this year to £900 million, according to the Sunday Times Rich List, released on April 24.\nAlan Howard, the cofounder of Brevan Howard, also fell from the number one spot after a devastating £460 million plunge in his wealth over the last year.\nNext year's list is likely to reveal an equally tough year for hedgies. Sterling hit 31-year lows against the dollar in 2016, oil prices are still deflated, and Brexit is on the horizon.\nThe Sunday Times, which lists the 1,000 wealthiest individuals and families in the UK, ranked the richest hedge fund managers in Britain. Business Insider took a look at the top 13 below:\n(All the ages of the people who made the list correspond to the time their fortunes were calculated, which was as of April 24, this year).","url":"https://www.businessinsider.com/sunday-times-rich-list-2016-hedge-fund-managers-uk-britain-2016-12"}
