{"authors":[],"date_download":"2018-10-22 22:20:00","date_modify":"2018-10-22 22:20:00","date_publish":"2014-05-09 19:59:18","description":"The Veterans Health Administration by the numbers -– who it serves, and how long they have to wait for care.","filename":"data/vaneerConsumption/TheVABytheNumbersHowBigIsItandWhoUsesIt.json","image_url":"https://nodeassets.nbcnews.com/cdnassets/projects/socialshareimages-bento/og-nbcnews1200x630.png","language":"en","localpath":"/home/avsp_here/news-please-repo//data/2018/10/22/nbcnews.com/storyline_va-hospital-scandal_va-numbers-how-big-it-who-uses-it-n101771_1540246800.html","title":"The VA By the Numbers: How Big Is It and Who Uses It?","title_page":"The VA By the Numbers: How Big Is It and Who Uses It?","title_rss":"NULL","source_domain":"nbcnews.com","text":"Breaking News Emails Get breaking news alerts and special reports. The news and stories that matter, delivered weekday mornings.\nHow big is the Veterans Health Administration?\n- 150 VA Hospitals\n- 820 VA Community-Based Outpatient Clinics\n- 300 VA Vet Centers, which offer counseling, suicide prevention and other services\nWho do these hospitals serve?\n- 5.69 million patients in 2013\n- 8.92 million people enrolled in VA health care system\n- 6.69 million life insurance policies supervised and administered by the VA\n- 3.84 million veterans receiving VA disability compensation\n- 2.03 million active VA home loan participants\n- 1.09 million VA education beneficiaries\n- 310,000 veterans receiving VA pensions\n- 70,000 VA vocational rehabilitation trainees\nHow bad is the VA’s benefits and disability claims backlog?\n- Pending disability claims peaked in March 2013 at 611,000\n- There were 344,000 claims as of April 2014 (a reduction of 44 percent)\n- On average, vets are waiting 119 days less for a decision than they were a year ago\n- VA’s national rate of accurately processing benefit and disability claims: 91 percent\n- President Obama pledged during his 2008 campaign to reduce the average wait time for VA claim decisions to 125 days by the end of 2015. Estimates of wait times at some VA facilities can exceed a year; the VA says it has lowered the average wait time by 119 days since 2013.\nHow much does it cost the taxpayer?\n- Estimated 2014 fiscal year VA budget: $150.7 billion\n- Budget requested for 2015: $163.9 billion\n- Estimated budget for hospital and medical care for veterans: $55.4 billion\n- VA represents an estimated 3.9 percent of the federal budget\nHow many veterans are there?\n- 21,882,153 total\n- 2.5 million served during Iraq/Afghanistan\n- 6.5 million served during the Gulf War\n- 7.3 million served during the Vietnam era\n- 2.1 million served during the Korean conflict\n- 1.2 million served during World War II\n- 5.5 million served during peacetime only\n(NOTE: categories are not mutually exclusive; veterans may have served during more than one conflict)\nWho are they?\n- Veteran population is 90 percent male, 10 percent female\n- 79.6 percent are white, 11.3 percent are black, 5.7 percent are Hispanic\n- 44.19 percent of the veteran population is 65 or older\n- Median annual income of veterans, including retirees: $36,264, as of 2012\n- 14.7 million veterans voted in the 2012 presidential election\n- 1.2 million veterans didn’t have health insurance in 2012\nSources: Department of Veterans Affairs, United States Census Bureau","url":"https://www.nbcnews.com/storyline/va-hospital-scandal/va-numbers-how-big-it-who-uses-it-n101771"}
