{"authors":["Trent Baker"],"date_download":"2018-10-30 20:48:32","date_modify":"2018-10-30 20:48:32","date_publish":"2017-02-04 17:02:23","description":"Per a New York Post report, a fight broke out Friday in New York City among people waiting to get a pair of Cleveland Cavaliers star LeBron James' new | Video","filename":"data/vaneerConsumption/WatchLargeFightBreaksOutOverNewLeBronJamesShoes.json","image_url":"https://media.breitbart.com/media/2017/01/lebron1.png","language":"en","localpath":"/home/avsp_here/news-please-repo//data/2018/10/30/breitbart.com/video_2017_02_04__1540932512.html","title":"Watch: Large Fight Breaks Out Over New LeBron James Shoes","title_page":"Watch: Large Fight Breaks Out Over New LeBron James Shoes | Breitbart","title_rss":"NULL","source_domain":"breitbart.com","text":"Per a New York Post report, a fight broke out Friday in New York City among people waiting to get a pair of Cleveland Cavaliers star LeBron James’ new LeBron 14 sneakers.\nVideo surfaced of the brawl, showing people punching and shoving each other outside of a Foot Locker.\nThe NYPD reportedly did not have information on the incident and could not say if anyone was arrested as part of the fighting.\nAlthough the LeBron 14 sneakers are set to be released February 10, Foot Locker sold a limited amount of the $175 basketball shoes Friday.\nFollow Trent Baker on Twitter @MagnifiTrent","url":"https://www.breitbart.com/video/2017/02/04/watch-large-fight-breaks-out-over-new-lebron-james-shoes/"}
